{"textures":{"1":"mcc:island_cosmetics/general/accessory/poseidons_trident/poseidon_trident"},"elements":[{"from":[6.9,12.2033,0.58934],"to":[9.1,17.4033,5.78934],"rotation":{"angle":45.0,"axis":"x","origin":[8.0,10.01777,8.0]},"faces":{"north":{"uv":[9.0,2.0,6.5,2.5],"texture":"#1","rotation":270},"east":{"uv":[9.0,0.0,6.5,2.5],"texture":"#1","rotation":270},"south":{"uv":[6.5,0.5,9.0,0.0],"texture":"#1","rotation":90},"west":{"uv":[6.5,2.5,9.0,0.0],"texture":"#1"},"up":{"uv":[6.5,0.0,7.0,2.5],"texture":"#1","rotation":180},"down":{"uv":[8.5,0.0,9.0,2.5],"texture":"#1"}}},{"from":[7.0,-2.8033,6.98223],"to":[9.0,16.1967,8.98223],"rotation":{"angle":0.0,"axis":"x","origin":[8.0,10.01777,8.0]},"faces":{"north":{"uv":[9.5,8.0,0.0,7.0],"texture":"#1","rotation":270},"east":{"uv":[9.5,7.0,0.0,8.0],"texture":"#1","rotation":270},"south":{"uv":[0.0,7.0,9.5,8.0],"texture":"#1","rotation":90},"west":{"uv":[0.0,8.0,9.5,7.0],"texture":"#1","rotation":90},"up":{"uv":[0.0,0.0,0.5,0.5],"texture":"#1","rotation":180},"down":{"uv":[0.0,0.0,0.5,0.5],"texture":"#1"}}},{"from":[8.0,16.83883,1.01777],"to":[8.0,29.83883,15.01777],"rotation":{"angle":0.0,"axis":"x","origin":[8.0,10.01777,8.0]},"faces":{"north":{"uv":[0.0,0.0,0.5,0.5],"texture":"#1","rotation":180},"east":{"uv":[6.5,0.0,0.0,7.0],"texture":"#1","rotation":270},"south":{"uv":[0.0,0.0,0.5,0.5],"texture":"#1"},"west":{"uv":[0.0,0.0,6.5,7.0],"texture":"#1","rotation":90},"up":{"uv":[0.0,0.0,0.5,0.5],"texture":"#1","rotation":180},"down":{"uv":[0.0,0.0,0.5,0.5],"texture":"#1"}}},{"from":[6.5,-6.8033,6.48223],"to":[9.5,0.1967,9.48223],"rotation":{"angle":0.0,"axis":"x","origin":[8.0,10.01777,8.0]},"faces":{"north":{"uv":[0.0,9.5,3.5,8.0],"texture":"#1","rotation":90},"east":{"uv":[3.5,8.0,0.0,9.5],"texture":"#1","rotation":270},"south":{"uv":[3.5,8.0,0.0,9.5],"texture":"#1","rotation":270},"west":{"uv":[0.0,8.0,3.5,9.5],"texture":"#1","rotation":90},"up":{"uv":[6.5,8.0,5.0,9.5],"texture":"#1","rotation":90},"down":{"uv":[5.0,8.0,3.5,9.5],"texture":"#1","rotation":270}}}],"display":{"thirdperson_righthand":{"translation":[1.25,1.25,3.5],"rotation":[-154.75,32.67,-155.01]},"thirdperson_lefthand":{"translation":[1.25,1.25,3.5],"rotation":[-154.75,32.67,-155.01]},"firstperson_righthand":{"translation":[3.63,3.7,0.38],"rotation":[-21.02,6.83,4.09],"scale":[0.42023,0.42023,0.42023]},"firstperson_lefthand":{"translation":[3.63,3.7,0.38],"rotation":[-21.02,6.83,4.09],"scale":[0.42023,0.42023,0.42023]},"ground":{"translation":[0.25,14.0,0.25],"rotation":[-47.04,0.0,0.0],"scale":[0.49805,0.49805,0.49805]},"gui":{"translation":[-1.0,-1.0,0.0],"rotation":[107.46,35.49,-123.83],"scale":[0.57383,0.57383,0.57383]},"head":{"translation":[0.0,-20.25,8.0],"rotation":[0.0,90.0,0.0],"scale":[1.7543,1.7543,1.7543]}},"credit":"Made with Blockbench","gui_light":"front"}